saturn_bot/__init__.py
saturn_bot/controller.py
saturn_bot/plugin/__init__.py
saturn_bot/plugin/grpc_controller_pb2.py
saturn_bot/plugin/grpc_controller_pb2.pyi
saturn_bot/plugin/grpc_controller_pb2_grpc.py
saturn_bot/plugin/grpc_stdio_pb2.py
saturn_bot/plugin/grpc_stdio_pb2.pyi
saturn_bot/plugin/grpc_stdio_pb2_grpc.py
saturn_bot/protocol/__init__.py
saturn_bot/protocol/v1/__init__.py
saturn_bot/protocol/v1/saturnbot_pb2.py
saturn_bot/protocol/v1/saturnbot_pb2.pyi
saturn_bot/protocol/v1/saturnbot_pb2_grpc.py
saturn_bot/sdk.py
saturn_bot/stdio.py
saturn_bot-0.7.0.dist-info/LICENSE
saturn_bot-0.7.0.dist-info/METADATA
saturn_bot-0.7.0.dist-info/WHEEL
saturn_bot-0.7.0.dist-info/RECORD
